MANIFEST.in
README
setup.py
cfncluster/__init__.py
cfncluster/cfncluster.py
cfncluster/cfnconfig.py
cfncluster/cli.py
cfncluster/config_sanity.py
cfncluster/easyconfig.py
cfncluster.egg-info/PKG-INFO
cfncluster.egg-info/SOURCES.txt
cfncluster.egg-info/dependency_links.txt
cfncluster.egg-info/entry_points.txt
cfncluster.egg-info/not-zip-safe
cfncluster.egg-info/requires.txt
cfncluster.egg-info/top_level.txt
cfncluster/examples/config
tests/__init__.py
tests/cfncluster-unittest.py